{"variants":{"facing=south,variant=alpha":{"model":"conquest:netherbrick_red_corner","y":180,"uvlock":true},"facing=west,variant=alpha":{"model":"conquest:netherbrick_red_corner","uvlock":true,"y":270},"facing=north,variant=alpha":{"model":"conquest:netherbrick_red_corner","uvlock":true},"facing=east,variant=alpha":{"model":"conquest:netherbrick_red_corner","y":90,"uvlock":true},"facing=south,variant=bravo":{"model":"conquest:pile_bones_corner","y":180,"uvlock":true},"facing=west,variant=bravo":{"model":"conquest:pile_bones_corner","uvlock":true,"y":270},"facing=north,variant=bravo":{"model":"conquest:pile_bones_corner","uvlock":true},"facing=east,variant=bravo":{"model":"conquest:pile_bones_corner","y":90,"uvlock":true},"facing=south,variant=charlie":{"model":"conquest:pile_skeletons_corner","y":180,"uvlock":true},"facing=west,variant=charlie":{"model":"conquest:pile_skeletons_corner","uvlock":true,"y":270},"facing=north,variant=charlie":{"model":"conquest:pile_skeletons_corner","uvlock":true},"facing=east,variant=charlie":{"model":"conquest:pile_skeletons_corner","y":90,"uvlock":true},"facing=south,variant=delta":{"model":"conquest:brick_romanvertical_corner","y":180,"uvlock":true},"facing=west,variant=delta":{"model":"conquest:brick_romanvertical_corner","uvlock":true,"y":270},"facing=north,variant=delta":{"model":"conquest:brick_romanvertical_corner","uvlock":true},"facing=east,variant=delta":{"model":"conquest:brick_romanvertical_corner","y":90,"uvlock":true}}}