{"variants":{"axis=y,variant=alpha":{"model":"conquest:cobblestone_normal_base"},"axis=x,variant=alpha":{"model":"conquest:cobblestone_normal_anvil","y":90},"axis=z,variant=alpha":{"model":"conquest:cobblestone_normal_anvil","y":180},"axis=none,variant=alpha":{"model":"conquest:none"},"axis=y,variant=bravo":{"model":"conquest:sandstone_normal_base"},"axis=x,variant=bravo":{"model":"conquest:sandstone_normal_anvil","y":90},"axis=z,variant=bravo":{"model":"conquest:sandstone_normal_anvil","y":180},"axis=none,variant=bravo":{"model":"conquest:none"},"axis=y,variant=charlie":{"model":"conquest:iron_normal_base"},"axis=x,variant=charlie":{"model":"conquest:iron_normal_anvil","y":90},"axis=z,variant=charlie":{"model":"conquest:iron_normal_anvil","y":180},"axis=none,variant=charlie":{"model":"conquest:none"},"axis=y,variant=delta":{"model":"conquest:bricks_normal_base"},"axis=x,variant=delta":{"model":"conquest:bricks_normal_anvil","y":90},"axis=z,variant=delta":{"model":"conquest:bricks_normal_anvil","y":180},"axis=none,variant=delta":{"model":"conquest:none"}}}