{"variants":{"variant=alpha":{"model":"conquest:planks_sprucenormal_wall_post"},"variant=bravo":{"model":"conquest:planks_birchnormal_wall_post"},"variant=charlie":{"model":"conquest:planks_junglenormal_wall_post"},"variant=delta":{"model":"conquest:planks_acacianormal_wall_post"},"variant=echo":{"model":"conquest:planks_darkoaknormal_wall_post"},"variant=fox":{"model":"conquest:log_rope_wall_post"},"variant=golf":{"model":"conquest:log_chain_wall_post"},"variant=hotel":{"model":"conquest:birch_carveddesign_wall_post"},"variant=india":{"model":"conquest:pillar_carvedwoodgilded_wall_post"},"variant=juliet":{"model":"conquest:oak_carveddesign_wall_post"},"variant=kilo":{"model":"conquest:beam_oak_wall_post"},"variant=lima":{"model":"conquest:planks_oak1_wall_post"},"variant=mike":{"model":"conquest:planks_reinforcedoak_wall_post"},"variant=november":{"model":"conquest:planks_oaknails_wall_post"},"variant=oscar":{"model":"conquest:planks_spruceironbound_wall_post"},"variant=papa":{"model":"conquest:planks_ashcolored_wall_post"}}}