{"variants":{"axis=y,variant=alpha":{"model":"conquest:planks_oaknormal_base"},"axis=x,variant=alpha":{"model":"conquest:planks_oaknormal_anvil","y":90},"axis=z,variant=alpha":{"model":"conquest:planks_oaknormal_anvil","y":180},"axis=none,variant=alpha":{"model":"conquest:none"},"axis=y,variant=bravo":{"model":"conquest:planks_birchnormal_base"},"axis=x,variant=bravo":{"model":"conquest:planks_birchnormal_anvil","y":90},"axis=z,variant=bravo":{"model":"conquest:planks_birchnormal_anvil","y":180},"axis=none,variant=bravo":{"model":"conquest:none"},"axis=y,variant=charlie":{"model":"conquest:planks_junglenormal_base"},"axis=x,variant=charlie":{"model":"conquest:planks_junglenormal_anvil","y":90},"axis=z,variant=charlie":{"model":"conquest:planks_junglenormal_anvil","y":180},"axis=none,variant=charlie":{"model":"conquest:none"},"axis=y,variant=delta":{"model":"conquest:planks_acacianormal_base"},"axis=x,variant=delta":{"model":"conquest:planks_acacianormal_anvil","y":90},"axis=z,variant=delta":{"model":"conquest:planks_acacianormal_anvil","y":180},"axis=none,variant=delta":{"model":"conquest:none"}}}