{"variants":{"variant=alpha":{"model":"conquest:planksblue"},"variant=bravo":{"model":"conquest:olddarkblueplanks"},"variant=charlie":{"model":"conquest:plank15ocean"},"variant=delta":{"model":"conquest:plankslightblue"},"variant=echo":{"model":"conquest:oldlightblueplanks"},"variant=fox":{"model":"conquest:plankspurple"},"variant=golf":{"model":"conquest:planksbrown"},"variant=hotel":{"model":"conquest:oldbrownplanks"},"variant=india":{"model":"conquest:barrel_apple"},"variant=juliet":{"model":"conquest:barrel_sack_apple"},"variant=kilo":{"model":"conquest:barrelapple2"},"variant=lima":{"model":"conquest:barrel_bread"},"variant=mike":{"model":"conquest:barrel_sack_bread"},"variant=november":{"model":"conquest:sackflour"},"variant=oscar":{"model":"conquest:barrel_cabbage"},"variant=papa":{"model":"conquest:barrel_sack_cabbage"}}}